{
 "autoExtract"                        : "UNSET",
 "extractPath"                        : null,
 "extractionInfo"                     : {
                                         "extractToFolder" : "/opt/JDownloader/Downloads",
                                         "files"           : [
                                                              "/opt/JDownloader/Downloads/Sherlock Holmes - Die neuen Fälle 046 - Für Königreich und Vaterland/01. Teil 1 - Die neuen Fälle, Fall 46_ Für Königreich und Vaterland.mp3",
                                                              "/opt/JDownloader/Downloads/Sherlock Holmes - Die neuen Fälle 046 - Für Königreich und Vaterland/02. Teil 2 - Die neuen Fälle, Fall 46_ Für Königreich und Vaterland.mp3",
                                                              "/opt/JDownloader/Downloads/Sherlock Holmes - Die neuen Fälle 046 - Für Königreich und Vaterland/03. Teil 3 - Die neuen Fälle, Fall 46_ Für Königreich und Vaterland.mp3",
                                                              "/opt/JDownloader/Downloads/Sherlock Holmes - Die neuen Fälle 046 - Für Königreich und Vaterland/04. Teil 4 - Die neuen Fälle, Fall 46_ Für Königreich und Vaterland.mp3",
                                                              "/opt/JDownloader/Downloads/Sherlock Holmes - Die neuen Fälle 046 - Für Königreich und Vaterland/05. Teil 5 - Die neuen Fälle, Fall 46_ Für Königreich und Vaterland.mp3",
                                                              "/opt/JDownloader/Downloads/Sherlock Holmes - Die neuen Fälle 046 - Für Königreich und Vaterland/06. Teil 6 - Die neuen Fälle, Fall 46_ Für Königreich und Vaterland.mp3",
                                                              "/opt/JDownloader/Downloads/Sherlock Holmes - Die neuen Fälle 046 - Für Königreich und Vaterland/07. Teil 7 - Die neuen Fälle, Fall 46_ Für Königreich und Vaterland.mp3",
                                                              "/opt/JDownloader/Downloads/Sherlock Holmes - Die neuen Fälle 046 - Für Königreich und Vaterland/08. Teil 8 - Die neuen Fälle, Fall 46_ Für Königreich und Vaterland.mp3",
                                                              "/opt/JDownloader/Downloads/Sherlock Holmes - Die neuen Fälle 046 - Für Königreich und Vaterland/09. Teil 9 - Die neuen Fälle, Fall 46_ Für Königreich und Vaterland.mp3",
                                                              "/opt/JDownloader/Downloads/Sherlock Holmes - Die neuen Fälle 046 - Für Königreich und Vaterland/10. Teil 10 - Die neuen Fälle, Fall 46_ Für Königreich und Vaterland.mp3",
                                                              "/opt/JDownloader/Downloads/Sherlock Holmes - Die neuen Fälle 046 - Für Königreich und Vaterland/11. Teil 11 - Die neuen Fälle, Fall 46_ Für Königreich und Vaterland.mp3",
                                                              "/opt/JDownloader/Downloads/Sherlock Holmes - Die neuen Fälle 046 - Für Königreich und Vaterland/12. Teil 12 - Die neuen Fälle, Fall 46_ Für Königreich und Vaterland.mp3",
                                                              "/opt/JDownloader/Downloads/Sherlock Holmes - Die neuen Fälle 046 - Für Königreich und Vaterland/13. Teil 13 - Die neuen Fälle, Fall 46_ Für Königreich und Vaterland.mp3",
                                                              "/opt/JDownloader/Downloads/Sherlock Holmes - Die neuen Fälle 046 - Für Königreich und Vaterland/14. Teil 14 - Die neuen Fälle, Fall 46_ Für Königreich und Vaterland.mp3",
                                                              "/opt/JDownloader/Downloads/Sherlock Holmes - Die neuen Fälle 046 - Für Königreich und Vaterland/15. Teil 15 - Die neuen Fälle, Fall 46_ Für Königreich und Vaterland.mp3",
                                                              "/opt/JDownloader/Downloads/Sherlock Holmes - Die neuen Fälle 046 - Für Königreich und Vaterland/16. Teil 16 - Die neuen Fälle, Fall 46_ Für Königreich und Vaterland.mp3",
                                                              "/opt/JDownloader/Downloads/Sherlock Holmes - Die neuen Fälle 046 - Für Königreich und Vaterland/17. Teil 17 - Die neuen Fälle, Fall 46_ Für Königreich und Vaterland.mp3",
                                                              "/opt/JDownloader/Downloads/Sherlock Holmes - Die neuen Fälle 046 - Für Königreich und Vaterland/18. Teil 18 - Die neuen Fälle, Fall 46_ Für Königreich und Vaterland.mp3",
                                                              "/opt/JDownloader/Downloads/Sherlock Holmes - Die neuen Fälle 046 - Für Königreich und Vaterland/19. Teil 19 - Die neuen Fälle, Fall 46_ Für Königreich und Vaterland.mp3",
                                                              "/opt/JDownloader/Downloads/Sherlock Holmes - Die neuen Fälle 046 - Für Königreich und Vaterland/20. Teil 20 - Die neuen Fälle, Fall 46_ Für Königreich und Vaterland.mp3",
                                                              "/opt/JDownloader/Downloads/Sherlock Holmes - Die neuen Fälle 046 - Für Königreich und Vaterland/21. Teil 21 - Die neuen Fälle, Fall 46_ Für Königreich und Vaterland.mp3",
                                                              "/opt/JDownloader/Downloads/Sherlock Holmes - Die neuen Fälle 046 - Für Königreich und Vaterland/22. Teil 22 - Die neuen Fälle, Fall 46_ Für Königreich und Vaterland.mp3",
                                                              "/opt/JDownloader/Downloads/Sherlock Holmes - Die neuen Fälle 046 - Für Königreich und Vaterland/23. Teil 23 - Die neuen Fälle, Fall 46_ Für Königreich und Vaterland.mp3",
                                                              "/opt/JDownloader/Downloads/Sherlock Holmes - Die neuen Fälle 046 - Für Königreich und Vaterland/24. Teil 24 - Die neuen Fälle, Fall 46_ Für Königreich und Vaterland.mp3",
                                                              "/opt/JDownloader/Downloads/Sherlock Holmes - Die neuen Fälle 046 - Für Königreich und Vaterland/25. Teil 25 - Die neuen Fälle, Fall 46_ Für Königreich und Vaterland.mp3",
                                                              "/opt/JDownloader/Downloads/Sherlock Holmes - Die neuen Fälle 046 - Für Königreich und Vaterland/26. Teil 26 - Die neuen Fälle, Fall 46_ Für Königreich und Vaterland.mp3",
                                                              "/opt/JDownloader/Downloads/Sherlock Holmes - Die neuen Fälle 046 - Für Königreich und Vaterland/27. Teil 27 - Die neuen Fälle, Fall 46_ Für Königreich und Vaterland.mp3",
                                                              "/opt/JDownloader/Downloads/Sherlock Holmes - Die neuen Fälle 046 - Für Königreich und Vaterland/28. Teil 28 - Die neuen Fälle, Fall 46_ Für Königreich und Vaterland.mp3",
                                                              "/opt/JDownloader/Downloads/Sherlock Holmes - Die neuen Fälle 046 - Für Königreich und Vaterland/29. Teil 29 - Die neuen Fälle, Fall 46_ Für Königreich und Vaterland.mp3",
                                                              "/opt/JDownloader/Downloads/Sherlock Holmes - Die neuen Fälle 046 - Für Königreich und Vaterland/30. Teil 30 - Die neuen Fälle, Fall 46_ Für Königreich und Vaterland.mp3",
                                                              "/opt/JDownloader/Downloads/Sherlock Holmes - Die neuen Fälle 046 - Für Königreich und Vaterland/31. Teil 31 - Die neuen Fälle, Fall 46_ Für Königreich und Vaterland.mp3",
                                                              "/opt/JDownloader/Downloads/Sherlock Holmes - Die neuen Fälle 046 - Für Königreich und Vaterland/32. Teil 32 - Die neuen Fälle, Fall 46_ Für Königreich und Vaterland.mp3",
                                                              "/opt/JDownloader/Downloads/Sherlock Holmes - Die neuen Fälle 046 - Für Königreich und Vaterland/33. Teil 33 - Die neuen Fälle, Fall 46_ Für Königreich und Vaterland.mp3",
                                                              "/opt/JDownloader/Downloads/Sherlock Holmes - Die neuen Fälle 046 - Für Königreich und Vaterland/34. Teil 34 - Die neuen Fälle, Fall 46_ Für Königreich und Vaterland.mp3",
                                                              "/opt/JDownloader/Downloads/Sherlock Holmes - Die neuen Fälle 046 - Für Königreich und Vaterland/35. Teil 35 - Die neuen Fälle, Fall 46_ Für Königreich und Vaterland.mp3",
                                                              "/opt/JDownloader/Downloads/Sherlock Holmes - Die neuen Fälle 046 - Für Königreich und Vaterland/36. Teil 36 - Die neuen Fälle, Fall 46_ Für Königreich und Vaterland.mp3",
                                                              "/opt/JDownloader/Downloads/Sherlock Holmes - Die neuen Fälle 046 - Für Königreich und Vaterland/37. Teil 37 - Die neuen Fälle, Fall 46_ Für Königreich und Vaterland.mp3",
                                                              "/opt/JDownloader/Downloads/Sherlock Holmes - Die neuen Fälle 046 - Für Königreich und Vaterland/38. Teil 38 - Die neuen Fälle, Fall 46_ Für Königreich und Vaterland.mp3",
                                                              "/opt/JDownloader/Downloads/Sherlock Holmes - Die neuen Fälle 046 - Für Königreich und Vaterland/39. Teil 39 - Die neuen Fälle, Fall 46_ Für Königreich und Vaterland.mp3",
                                                              "/opt/JDownloader/Downloads/Sherlock Holmes - Die neuen Fälle 046 - Für Königreich und Vaterland/40. Teil 40 - Die neuen Fälle, Fall 46_ Für Königreich und Vaterland.mp3",
                                                              "/opt/JDownloader/Downloads/Sherlock Holmes - Die neuen Fälle 046 - Für Königreich und Vaterland/41. Teil 41 - Die neuen Fälle, Fall 46_ Für Königreich und Vaterland.mp3",
                                                              "/opt/JDownloader/Downloads/Sherlock Holmes - Die neuen Fälle 046 - Für Königreich und Vaterland/42. Teil 42 - Die neuen Fälle, Fall 46_ Für Königreich und Vaterland.mp3",
                                                              "/opt/JDownloader/Downloads/Sherlock Holmes - Die neuen Fälle 046 - Für Königreich und Vaterland/43. Teil 43 - Die neuen Fälle, Fall 46_ Für Königreich und Vaterland.mp3",
                                                              "/opt/JDownloader/Downloads/Sherlock Holmes - Die neuen Fälle 046 - Für Königreich und Vaterland/44. Teil 44 - Die neuen Fälle, Fall 46_ Für Königreich und Vaterland.mp3",
                                                              "/opt/JDownloader/Downloads/Sherlock Holmes - Die neuen Fälle 046 - Für Königreich und Vaterland/45. Teil 45 - Die neuen Fälle, Fall 46_ Für Königreich und Vaterland.mp3",
                                                              "/opt/JDownloader/Downloads/Sherlock Holmes - Die neuen Fälle 046 - Für Königreich und Vaterland/46. Teil 46 - Die neuen Fälle, Fall 46_ Für Königreich und Vaterland.mp3",
                                                              "/opt/JDownloader/Downloads/Sherlock Holmes - Die neuen Fälle 046 - Für Königreich und Vaterland/47. Teil 47 - Die neuen Fälle, Fall 46_ Für Königreich und Vaterland.mp3",
                                                              "/opt/JDownloader/Downloads/Sherlock Holmes - Die neuen Fälle 046 - Für Königreich und Vaterland/Cover.jpg",
                                                              "/opt/JDownloader/Downloads/Sherlock Holmes - Die neuen Fälle 046 - Für Königreich und Vaterland/Hoerbuchsammlung - EINZELN LADBAR - Pastebin.com.html",
                                                              "/opt/JDownloader/Downloads/Sherlock Holmes - Die neuen Fälle 046 - Für Königreich und Vaterland/HOERBUCH_SAMMLUNG.txt",
                                                              "/opt/JDownloader/Downloads/Sherlock Holmes - Die neuen Fälle 046 - Für Königreich und Vaterland/Rapidgator 12TB_REFLINK für Unterstützung. DANKE.txt"
                                                             ]
                                        },
 "finalPassword"                      : null,
 "ifFileExistsAction"                 : null,
 "passwords"                          : [],
 "removeDownloadLinksAfterExtraction" : "UNSET",
 "removeFilesAfterExtraction"         : "UNSET"
}