{
 "autoExtract"                        : "UNSET",
 "extractPath"                        : null,
 "extractionInfo"                     : {
                                         "extractToFolder" : "/opt/JDownloader/Downloads",
                                         "files"           : [
                                                              "/opt/JDownloader/Downloads/Arthur Conan Doyle - Sherlock Holmes Chronicles 071 - Die Spur des Falke/Die Spur des Falke - 01.mp3",
                                                              "/opt/JDownloader/Downloads/Arthur Conan Doyle - Sherlock Holmes Chronicles 071 - Die Spur des Falke/Die Spur des Falke - 02.mp3",
                                                              "/opt/JDownloader/Downloads/Arthur Conan Doyle - Sherlock Holmes Chronicles 071 - Die Spur des Falke/Die Spur des Falke - 03.mp3",
                                                              "/opt/JDownloader/Downloads/Arthur Conan Doyle - Sherlock Holmes Chronicles 071 - Die Spur des Falke/Die Spur des Falke - 04.mp3",
                                                              "/opt/JDownloader/Downloads/Arthur Conan Doyle - Sherlock Holmes Chronicles 071 - Die Spur des Falke/Die Spur des Falke - 05.mp3",
                                                              "/opt/JDownloader/Downloads/Arthur Conan Doyle - Sherlock Holmes Chronicles 071 - Die Spur des Falke/Die Spur des Falke - 06.mp3",
                                                              "/opt/JDownloader/Downloads/Arthur Conan Doyle - Sherlock Holmes Chronicles 071 - Die Spur des Falke/Die Spur des Falke - 07.mp3",
                                                              "/opt/JDownloader/Downloads/Arthur Conan Doyle - Sherlock Holmes Chronicles 071 - Die Spur des Falke/Die Spur des Falke - 08.mp3",
                                                              "/opt/JDownloader/Downloads/Arthur Conan Doyle - Sherlock Holmes Chronicles 071 - Die Spur des Falke/Die Spur des Falke - 09.mp3",
                                                              "/opt/JDownloader/Downloads/Arthur Conan Doyle - Sherlock Holmes Chronicles 071 - Die Spur des Falke/Die Spur des Falke - 10.mp3",
                                                              "/opt/JDownloader/Downloads/Arthur Conan Doyle - Sherlock Holmes Chronicles 071 - Die Spur des Falke/Die Spur des Falke - 11.mp3",
                                                              "/opt/JDownloader/Downloads/Arthur Conan Doyle - Sherlock Holmes Chronicles 071 - Die Spur des Falke/Die Spur des Falke - 12.mp3",
                                                              "/opt/JDownloader/Downloads/Arthur Conan Doyle - Sherlock Holmes Chronicles 071 - Die Spur des Falke/folder.jpg",
                                                              "/opt/JDownloader/Downloads/Arthur Conan Doyle - Sherlock Holmes Chronicles 071 - Die Spur des Falke/Hoerbuchsammlung - EINZELN LADBAR - Pastebin.com.html",
                                                              "/opt/JDownloader/Downloads/Arthur Conan Doyle - Sherlock Holmes Chronicles 071 - Die Spur des Falke/HOERBUCH_SAMMLUNG.txt",
                                                              "/opt/JDownloader/Downloads/Arthur Conan Doyle - Sherlock Holmes Chronicles 071 - Die Spur des Falke/Rapidgator 12TB_REFLINK für Unterstützung. DANKE.txt",
                                                              "/opt/JDownloader/Downloads/Arthur Conan Doyle - Sherlock Holmes Chronicles 071 - Die Spur des Falke/_play.m3u"
                                                             ]
                                        },
 "finalPassword"                      : null,
 "ifFileExistsAction"                 : null,
 "passwords"                          : [],
 "removeDownloadLinksAfterExtraction" : "UNSET",
 "removeFilesAfterExtraction"         : "UNSET"
}