{
 "autoExtract"                        : "UNSET",
 "extractPath"                        : null,
 "extractionInfo"                     : {
                                         "extractToFolder" : "/opt/JDownloader/Downloads/NarutoShippuuden",
                                         "files"           : [
                                                              "/opt/JDownloader/Downloads/NarutoShippuuden/[TnF]Naruto_Shippuuden_441[720p][E81D76A2].mp4"
                                                             ]
                                        },
 "finalPassword"                      : null,
 "ifFileExistsAction"                 : null,
 "passwords"                          : [],
 "removeDownloadLinksAfterExtraction" : "UNSET",
 "removeFilesAfterExtraction"         : "UNSET"
}